{
    "meta": {
        "caption": "Фиолетовая грядка",
        "navigator": "падший77",
        "date": "17.02.2013",
        "size": {
            "width": 700,
            "height": 700
        }
    },
    "objects": [
        {
            "type": "Feature",
            "geometry": {
                "type": "Point",
                "coordinates": [
                    194,
                    -338
                ]
            },
            "properties": {
                "type": "boss",
                "x": 194,
                "y": 338,
                "caption": "Фиолетовый",
                "class": "flower",
                "mode": "quest"
            }
        }
    ]
}